nmrgnn/__init__.py
nmrgnn/layers.py
nmrgnn/library.py
nmrgnn/losses.py
nmrgnn/main.py
nmrgnn/metrics.py
nmrgnn/model.py
nmrgnn/version.py
nmrgnn/models/baseline/saved_model.pb
nmrgnn/models/baseline/variables/variables.data-00000-of-00001
nmrgnn/models/baseline/variables/variables.index
nmrgnn-0.7.dist-info/LICENSE
nmrgnn-0.7.dist-info/METADATA
nmrgnn-0.7.dist-info/WHEEL
nmrgnn-0.7.dist-info/entry_points.txt
nmrgnn-0.7.dist-info/top_level.txt
nmrgnn-0.7.dist-info/zip-safe
nmrgnn-0.7.dist-info/RECORD
