Metadata-Version: 2.1
Name: nmrgnn
Version: 0.7
Summary: Chemical shift predictor
Home-page: https://github.com/ur-whitelab/nmrgnn
Author: Ziyue Yang, Andrew White
Author-email: andrew.white@rochester.edu
License: MIT
Platform: UNKNOWN
Classifier: Programming Language :: Python :: 3
Classifier: License :: OSI Approved :: MIT License
Classifier: Operating System :: OS Independent
Classifier: Topic :: Scientific/Engineering :: Bio-Informatics
Classifier: Topic :: Scientific/Engineering :: Artificial Intelligence
License-File: LICENSE
Requires-Dist: tensorflow (>=2.3)
Requires-Dist: MDAnalysis (>=2)
Requires-Dist: click
Requires-Dist: numpy
Requires-Dist: pandas
Requires-Dist: tqdm
Requires-Dist: nmrgnn-data (>=0.7)
Requires-Dist: keras-tuner (==1.0.2)
